{
   "datasetVersion": {
      "metadataBlocks": {
         "citation": {
            "fields": [
               {
                  "value": "MIRRI0025059",
                  "typeClass": "primitive",
                  "multiple": false,
                  "typeName": "title"
               },
               {
                  "typeName": "alternativeURL",
                  "multiple": false,
                  "typeClass": "primitive",
                  "value": "https://catalog.mirri.org/page/Strains_display/25059"
               },
               {
                  "value": [
                     {
                        "authorName": {
                           "value": "CIRM-CFBP",
                           "typeClass": "primitive",
                           "multiple": false,
                           "typeName": "authorName"
                        },
                        "authorAffiliation": {
                           "value": "CIRM-CFBP",
                           "typeClass": "primitive",
                           "multiple": false,
                           "typeName": "authorAffiliation"
                        }
                     }
                  ],
                  "typeClass": "compound",
                  "multiple": true,
                  "typeName": "author"
               },
               {
                  "value": [
                     {
                        "datasetContactEmail": {
                           "typeClass": "primitive",
                           "multiple": false,
                           "typeName": "datasetContactEmail",
                           "value": " cfbp@inrae.fr"
                        },
                        "datasetContactName": {
                           "typeClass": "primitive",
                           "multiple": false,
                           "typeName": "datasetContactName",
                           "value": "CIRM-CFBP"
                        }
                     }
                  ],
                  "typeClass": "compound",
                  "multiple": true,
                  "typeName": "datasetContact"
               },
               {
                  "value": [
                     {
                        "dsDescriptionValue": {
                           "value": "Organism type: Bacteria ;  Taxon name: Clavibacter michiganensis ;  Collection: CFBP 7467 ;  Country: Unspecified ",
                           "multiple": false,
                           "typeClass": "primitive",
                           "typeName": "dsDescriptionValue"
                        }
                     }
                  ],
                  "typeClass": "compound",
                  "multiple": true,
                  "typeName": "dsDescription"
               },
               {
                  "value": [
                     "Medicine, Health and Life Sciences"
                  ],
                  "typeClass": "controlledVocabulary",
                  "multiple": true,
                  "typeName": "subject"
               },
               {
                  "value": [
                     {
                        "keywordValue": {
                           "typeName": "keywordValue",
                           "multiple": false,
                           "typeClass": "primitive",
                           "value": "Microorganism"
                        },
                        "keywordVocabularyURI": {
                           "typeName": "keywordVocabularyURI",
                           "multiple": false,
                           "typeClass": "primitive",
                           "value": "https://bioportal.bioontology.org/ontologies/ADCAD/?p=classes&conceptid=https://purl.dataone.org/odo/ADCAD_00025"
                        }
                     },
                     {
                        "keywordValue": {
                           "typeName": "keywordValue",
                           "multiple": false,
                           "typeClass": "primitive",
                           "value": "Bacteria"
                        },
                        "keywordVocabularyURI": {
                           "typeName": "keywordVocabularyURI",
                           "multiple": false,
                           "typeClass": "primitive",
                           "value": "https://lpsn.dsmz.de/domain/bacteria-1"
                        }
                     }
                  ],
                  "typeName": "keyword",
                  "multiple": true,
                  "typeClass": "compound"
               }
            ],
            "displayName": "Citation Metadata"
         }
      }
   }
}